{
	"archive" : {},
	"artifacts" : 
	[
		{
			"path" : "utils/libutils.a"
		}
	],
	"backtrace" : 1,
	"backtraceGraph" : 
	{
		"commands" : 
		[
			"add_library",
			"add_compile_options",
			"include_directories"
		],
		"files" : 
		[
			"utils/CMakeLists.txt",
			"CMakeLists.txt"
		],
		"nodes" : 
		[
			{
				"file" : 0
			},
			{
				"command" : 0,
				"file" : 0,
				"line" : 2,
				"parent" : 0
			},
			{
				"file" : 1
			},
			{
				"command" : 1,
				"file" : 1,
				"line" : 15,
				"parent" : 2
			},
			{
				"command" : 1,
				"file" : 1,
				"line" : 18,
				"parent" : 2
			},
			{
				"command" : 2,
				"file" : 1,
				"line" : 21,
				"parent" : 2
			},
			{
				"command" : 2,
				"file" : 0,
				"line" : 1,
				"parent" : 0
			}
		]
	},
	"compileGroups" : 
	[
		{
			"compileCommandFragments" : 
			[
				{
					"backtrace" : 3,
					"fragment" : "-O3"
				},
				{
					"backtrace" : 3,
					"fragment" : "-funroll-loops"
				},
				{
					"backtrace" : 4,
					"fragment" : "-fPIC"
				},
				{
					"fragment" : "-std=gnu++14"
				}
			],
			"includes" : 
			[
				{
					"backtrace" : 5,
					"path" : "/home/pi/ugv_ws/src/ugv_else/gmapping/openslam_gmapping/include"
				},
				{
					"backtrace" : 6,
					"path" : "/home/pi/ugv_ws/src/ugv_else/gmapping/openslam_gmapping/utils/."
				}
			],
			"language" : "CXX",
			"languageStandard" : 
			{
				"backtraces" : 
				[
					1
				],
				"standard" : "14"
			},
			"sourceIndexes" : 
			[
				0,
				1
			]
		}
	],
	"id" : "utils::@c810615cce0f7acb82dc",
	"name" : "utils",
	"nameOnDisk" : "libutils.a",
	"paths" : 
	{
		"build" : "utils",
		"source" : "utils"
	},
	"sourceGroups" : 
	[
		{
			"name" : "Source Files",
			"sourceIndexes" : 
			[
				0,
				1
			]
		}
	],
	"sources" : 
	[
		{
			"backtrace" : 1,
			"compileGroupIndex" : 0,
			"path" : "utils/movement.cpp",
			"sourceGroupIndex" : 0
		},
		{
			"backtrace" : 1,
			"compileGroupIndex" : 0,
			"path" : "utils/stat.cpp",
			"sourceGroupIndex" : 0
		}
	],
	"type" : "STATIC_LIBRARY"
}
